.DS_Store
calc11/__init__.py
calc11/calc11.py
calc11/data/DE421_big_Endian
calc11/data/DE421_little_Endian
calc11/data/Makefile.am
calc11/data/ocean_load.coef
calc11/data/ocean_pole_tide.coef
calc11/data/tilt.dat
calc11/data/usno_finals.erp
calc11/data/ut1ls.dat
calc11/lib/empty.txt
calc11/src/a_out.h
calc11/src/a_out.i
calc11/src/adrvr.f
calc11/src/ainit.f
calc11/src/almacalc.f
calc11/src/almaout.c
calc11/src/almastub.f
calc11/src/astrm.f
calc11/src/c2poly.i
calc11/src/calc11_wrapper.f90
calc11/src/catiu.f
calc11/src/catmm.f
calc11/src/caxom.f
calc11/src/ccon.i
calc11/src/cctiu.f
calc11/src/cdiuu.f
calc11/src/cdtdb.f
calc11/src/cetdm.f
calc11/src/cm20u.f
calc11/src/cmabd.f
calc11/src/cmatu.f
calc11/src/cmwob11.i
calc11/src/cmxsr11.i
calc11/src/cmxst11.i
calc11/src/cmxut11.i
calc11/src/cnutm.f
calc11/src/cnutu.f
calc11/src/cnutu6.f
calc11/src/cobsn11.i
calc11/src/cocem.f
calc11/src/config.h
calc11/src/cpepu.f
calc11/src/cphys11.i
calc11/src/cptdm.f
calc11/src/crosu.f
calc11/src/csitm.f
calc11/src/csolsys11.i
calc11/src/ctheu.f
calc11/src/cuser11.i
calc11/src/cut1m.f
calc11/src/cuvm.f
calc11/src/cvecu.f
calc11/src/cwobm.f
calc11/src/d_input.i
calc11/src/difx_input.h
calc11/src/difx_tcal.h
calc11/src/difxcalc.h
calc11/src/difxio.h
calc11/src/difxiohelper.c
calc11/src/dkill.f
calc11/src/dsitu.f
calc11/src/fitpoly_.c
calc11/src/get2s.i
calc11/src/hardisp.f
calc11/src/input11.i
calc11/src/param11.i
calc11/src/parsedifx.h
calc11/src/parsevis.h
calc11/src/poly.h
calc11/src/put2s.i
radio_telescope_delay_model-0.0.2.dist-info/LICENSE
radio_telescope_delay_model-0.0.2.dist-info/METADATA
radio_telescope_delay_model-0.0.2.dist-info/WHEEL
radio_telescope_delay_model-0.0.2.dist-info/top_level.txt
radio_telescope_delay_model-0.0.2.dist-info/RECORD
