Metadata-Version: 2.1
Name: radio-telescope-delay-model
Version: 0.0.2
Summary: Radio Telescope Delay Model
Home-page: https://github.com/casangi/radio_telescope_delay_model
Author: National Radio Astronomy Observatory
Author-email: casa-feedback@nrao.edu
License: Apache-2.0
Platform: UNKNOWN
Requires-Dist: numpy (>=1.18.1)
